captchaSaz/__init__.py
captchaSaz/fonts/Carmitta.ttf
captchaSaz/fonts/Lemon Shake Shake.ttf
captchaSaz/fonts/Meditative.ttf
captchaSaz/fonts/Pusing Kali.ttf
captchaSaz/fonts/Southport.ttf
captchasaz-2.0.4.dist-info/licenses/LICENSE
captchasaz-2.0.4.dist-info/METADATA
captchasaz-2.0.4.dist-info/WHEEL
captchasaz-2.0.4.dist-info/top_level.txt
captchasaz-2.0.4.dist-info/RECORD
