Metadata-Version: 2.4
Name: captchaSaz
Version: 2.0.4
Summary: This is a python-package meant to create automatic captcha
Author-email: UndrDsk0M <its1.ehsan@gmail.com>
License: MIT
Project-URL: Homepage, https://github.com/UndrDsk0M/captcha_generator
Classifier: Programming Language :: Python :: 3
Classifier: License :: OSI Approved :: MIT License
Classifier: Operating System :: OS Independent
Requires-Python: >=3.7
License-File: LICENSE
Requires-Dist: pillow<=11.3.0
Dynamic: license-file
